quick_actions/ActionDispatcher.py
quick_actions/CLI.py
quick_actions/MenuLoader.py
quick_actions/WhatToDoMenu.py
quick_actions/constants.py
quick_actions/main.py
quick_actions/config_processing/ActionProcessor.py
quick_actions/config_processing/ConfigProvider.py
quick_actions/config_processing/config_classes/Action.py
quick_actions/runners/CommandRunner.py
quick_actions/runners/ScriptRunner.py
quick_actions-0.0.5.dist-info/METADATA
quick_actions-0.0.5.dist-info/WHEEL
quick_actions-0.0.5.dist-info/entry_points.txt
quick_actions-0.0.5.dist-info/licenses/LICENSE
quick_actions-0.0.5.dist-info/RECORD
